Workbook

Sheet 第1题答案
B2: 销量(Q) | C2: 900
C4: 单位：元
B5: 平均每双销售价格(p) | C5: =150 -> 150
B6: 每双可变成本(v)： | C6: 54
B7: 固定成本(F)： | C7: 30000
B9: 单位边际贡献 | C9: =C5-C6 -> 96
B10: 边际贡献率 | C10: =C9/C5 -> 0.64
B11: 销售收益(R) | C11: =C2*C5 -> 135000
B12: 总成本(C) | C12: =C6*C2+C7 -> 78600
B13: 利润(π) | C13: =C11-C12 -> 56400
B15: 盈亏平衡销量(Q0) | C15: =C7/C9 -> 312.5
B16: 盈亏平衡销售收益(R0) | C16: =C15*C5 -> 46875
B19: 目标销量 | C19: 1000
B20: 目标销量下收益 | C20: =C5*C19 -> 150000
B21: 目标销量下成本 | C21: =C7+C6*C19 -> 84000
B22: 目标利润 | C22: =C20-C21 -> 66000
B23: 安全边际(S) | C23: =C19-C15 -> 687.5
B24: 安全边际率(s) | C24: =C23/C19 -> 0.6875

Sheet 第2题答案
C3: 月份（T） | E3: 20 | G3: 月份 | H3: 方案一 | I3: 方案二
H4: =D8 -> 240 | I4: =E8 -> 160
D5: 方案一 | E5: 方案二 | G5: 13 | H5: 156 | I5: 20
C6: 免租金月份 | E6: 12 | G6: 36 | H6: 432 | I6: 480
C7: 每月租金 | D7: 12 | E7: 20
C8: T时刻租金 | D8: =E3*D7 -> 240 | E8: =(E3-E6)*E7 -> 160 | G8: 相对盈亏平衡点垂直参考线
G9: =$E$10 -> 30 | H9: 500
C10: 两方案的相对盈亏平衡点T0 | E10: 30 | G10: =$E$10 -> 30 | H10: =E11 -> 360
C11: T0时的租金 | E11: =E10*D7 -> 360 | G11: =$E$10 -> 30 | H11: 0
C13: 结论文字 | G13: 当前月份垂直参考线
C14: =C3&"="&E3 -> 月份（T）=20 | G14: =$E$3 -> 20 | H14: 500
C15: ="决策结论：最佳方案是"&IF(E8<D8,"方案二",IF(E8>D8,"方案一","皆可")) -> 决策结论：最佳方案是方案二 | G15: =$E$3 -> 20 | H15: =E8 -> 160
G16: =$E$3 -> 20 | H16: =D8 -> 240
G17: =$E$3 -> 20 | H17: 0

Sheet 第3题答案
B2: 单价折扣率 | C2: =D2/100 -> 0.05 | D2: 5
B3: 折扣阈限值1 | C3: =D3 -> 1300 | D3: 1300 | F3: =C15 -> 118000 | G3: 11000 | H3: 12000 | I3: 13000 | J3: 14000 | K3: 15000 | L3: 16000 | M3: 17000 | N3: 18000 | P3: =C15 -> 118000 | Q3: 15000
B4: 单价折扣率2 | C4: 0.1 | F4: 300 | G4: 94000 | H4: 102000 | I4: 110000 | J4: 118000 | K4: 126000 | L4: 134000 | M4: 142000 | N4: 150000 | P4: =F4 -> 300 | Q4: 126000
B5: 折扣阈限值2 | C5: 1800 | F5: 400 | G5: 90500 | H5: 98000 | I5: 105500 | J5: 113000 | K5: 120500 | L5: 128000 | M5: 135500 | N5: 143000 | P5: =F5 -> 400 | Q5: 120500
B6: 年需求量 | C6: =Q3 -> 15000 | F6: 500 | G6: 89200 | H6: 96400 | I6: 103600 | J6: 110800 | K6: 118000 | L6: 125200 | M6: 132400 | N6: 139600 | P6: =F6 -> 500 | Q6: 118000
B7: 一次订货的订货成本 | C7: 600 | F7: 600 | G7: 89000 | H7: 96000 | I7: 103000 | J7: 110000 | K7: 117000 | L7: 124000 | M7: 131000 | N7: 138000 | P7: =F7 -> 600 | Q7: 117000
B8: 单位年储存成本 | C8: 40 | F8: 700 | G8: 89428.571 | H8: 96285.714 | I8: 103142.86 | J8: 110000 | K8: 116857.14 | L8: 123714.29 | M8: 130571.43 | N8: 137428.57 | P8: =F8 -> 700 | Q8: 116857.14
B9: 名义采购单价 | C9: 6 | F9: 800 | G9: 90250 | H9: 97000 | I9: 103750 | J9: 110500 | K9: 117250 | L9: 124000 | M9: 130750 | N9: 137500 | P9: =F9 -> 800 | Q9: 117250
B10: 实际采购单价 | C10: =IF(C11>=C3,IF(C11>=C5,C9*(1-C4),C9*(1-C2)),C9) -> 6 | F10: 900 | G10: 91333.333 | H10: 98000 | I10: 104666.67 | J10: 111333.33 | K10: 118000 | L10: 124666.67 | M10: 131333.33 | N10: 138000 | P10: =F10 -> 900 | Q10: 118000
B11: 订货量 | C11: 900 | F11: =C3-0.001 -> 1299.999 | G11: 97076.907 | H11: 103538.45 | I11: 109999.98 | J11: 116461.52 | K11: 122923.06 | L11: 129384.6 | M11: 135846.14 | N11: 142307.68 | P11: =F11 -> 1299.999 | Q11: 122923.06
B12: 年订货成本 | C12: =C6/C11*C7 -> 10000 | F12: =C3 -> 1300 | G12: 93776.923 | H12: 99938.462 | I12: 106100 | J12: 112261.54 | K12: 118423.08 | L12: 124584.62 | M12: 130746.15 | N12: 136907.69 | P12: =F12 -> 1300 | Q12: 118423.08
B13: 年储存成本 | C13: =C8*C11/2 -> 18000 | F13: =C5-0.01 -> 1799.99 | G13: 102366.49 | H13: 108399.82 | I13: 114433.16 | J13: 120466.49 | K13: 126499.83 | L13: 132533.16 | M13: 138566.5 | N13: 144599.83 | P13: =F13 -> 1799.99 | Q13: 126499.83
B14: 年采购成本 | C14: =C6*C10 -> 90000 | F14: =C5 -> 1800 | G14: 99066.667 | H14: 104800 | I14: 110533.33 | J14: 116266.67 | K14: 122000 | L14: 127733.33 | M14: 133466.67 | N14: 139200 | P14: =F14 -> 1800 | Q14: 122000
B15: 年总成本 | C15: =C12+C13+C14 -> 118000 | F15: 3500 | G15: 131285.71 | H15: 136857.14 | I15: 142428.57 | J15: 148000 | K15: 153571.43 | L15: 159142.86 | M15: 164714.29 | N15: 170285.71 | P15: =F15 -> 3500 | Q15: 153571.43
B17: 经济订货量(EOQ) | C17: =SQRT(2*C6*C7/C8) -> 670.82039 | G17: =C15 -> 118000
B18: EOQ下的年订货成本 | C18: =C6/C17*C7 -> 13416.408 | F18: 670 | G18: 116832.84
B19: EOQ下的年储存成本 | C19: =C17/2*C8 -> 13416.408 | F19: 1300 | G19: 118423.08
B20: EOQ下的年采购成本 | C20: =C9*C6 -> 90000 | F20: 1800 | G20: 122000
B21: EOQ下的年总成本 | C21: =C18+C19+C20 -> 116832.82
B23: 最低年总成本 | C23: =INDEX(F18:F20,MATCH(C24,G18:G20,0)) -> 670
B24: 最优订货量 | C24: =MIN(G18:G20) -> 116832.84
B26: ="单价折扣率="&C2*100&"%" -> 单价折扣率=5%
B27: ="年需求量="&C6 -> 年需求量=15000
B28: =IF(C15>C21,"按照经济订货量 "&ROUND(C17,0),"按照折扣阈限值"&C3)&"件订货" -> 按照经济订货量 671件订货

Sheet 第4题答案
A1: =MAX($C$13) -> 54193.548
A2: =COUNT($C$12:$E$12) -> 3
A3: {=$C$12:$E$12>=0} -> TRUE
A4: {=$F$8:$F$9<=第4题答案!$G$8:$G$9} -> TRUE
A5: ={100,100,0.000001,0.05,FALSE,FALSE,FALSE,1,1,1,0.0001,FALSE} -> 100
C7: A | D7: B | E7: C | F7: 用量 | G7: 资源限量
B8: 材料(kg) | C8: 1.5 | D8: 1.2 | E8: 4 | F8: {=SUM(C8:E8*$C$12:$E$12)} -> 8000 | G8: 8000
B9: 设备(台时) | C9: 3 | D9: 1.6 | E9: 1.2 | F9: {=SUM(C9:E9*$C$12:$E$12)} -> 6000 | G9: 6000
B10: 利润(元/件) | C10: 10 | D10: 14 | E10: 12
B12: 产量 | C12: 0 | D12: 2903.2258 | E12: 1129.0323
B13: 利润 | C13: {=SUM(C10:E10*C12:E12)} -> 54193.548

Sheet 第5题答案
B2: 原料 | C2: 甲 | D2: 乙 | E2: 丙 | F2: 原料成本 （元/公斤） | G2: 每月限制用量（公斤）
B3: A | C3: >=60% | D3: >=15% | F3: 2 | G3: 2000
B4: B | F4: 1.5 | G4: 2500
B5: C | C5: <=20% | D5: <=60% | E5: <=50% | F5: 1 | G5: 1200
B6: 加工费 （元/公斤） | C6: 0.5 | D6: 0.4 | E6: 0.3
B7: 售价 （元/公斤） | C7: 3.4 | D7: 2.85 | E7: 2.25
B10: 原料 | C10: 甲 | D10: 含量 比例 | E10: 含量 控制 | F10: 乙 | G10: 含量 比例 | H10: 含量 控制 | I10: 丙 | J10: 含量 比例 | K10: 含量 控制 | L10: 原料 总量 | M10: 原料成本 （元/公斤） | N10: 每月限制用量（公斤）
B11: A | C11: 1525.9333 | D11: =C11/C14 -> 0.6 | E11: 0.6 | F11: 473.06667 | G11: =F11/F14 -> 0.15 | H11: 0.15 | I11: 1 | L11: =C11+F11+I11 -> 2000 | M11: 2 | N11: 2000
B12: B | C12: 508.64471 | F12: 1990.3553 | I12: 1 | L12: =C12+F12+I12 -> 2500 | M12: 1.5 | N12: 2500
B13: C | C13: 508.64418 | D13: =C13/C14 -> 0.1999999 | E13: 0.2 | F13: 690.35582 | G13: =F13/F14 -> 0.21889805 | H13: 0.6 | I13: 1 | J13: =I13/I14 -> 0.33333333 | K13: 0.5 | L13: =C13+F13+I13 -> 1200 | M13: 1 | N13: 1200
B14: 产量 | C14: =SUM(C11:C13) -> 2543.2222 | F14: =SUM(F11:F13) -> 3153.7778 | I14: =SUM(I11:I13) -> 3
B15: 加工费 （元/公斤） | C15: 0.5 | F15: 0.4 | I15: 0.3
B16: 售价 （元/公斤） | C16: 3.4 | F16: 2.85 | I16: 2.25
B17: 收益 | C17: =C16*C14 -> 8646.9556 | F17: =F16*F14 -> 8988.2667 | I17: =I16*I14 -> 6.75
B18: 成本 | C18: =C11*$M$11+C12*$M$12+C13*$M$13+C14*C15 -> 5595.089 | F18: =F11*$M$11+F12*$M$12+F13*$M$13+F14*F15 -> 5883.5332 | I18: =I11*$M$11+I12*$M$12+I13*$M$13+I14*I15 -> 5.4
B19: 利润 | C19: =C17-C18 -> 3051.8665 | F19: =F17-F18 -> 3104.7335 | I19: =I17-I18 -> 1.35
B21: 总利润： | C21: =C19+F19+I19 -> 6157.95
B24: =MAX($C$21) -> 6157.95
B25: =COUNT($C$11:$C$13,$F$11:$F$13,$I$11:$I$13) -> 9
B26: {=$L$11:$L$13<=第5题答案!$N$11:$N$13} -> TRUE
B27: {=$C$11:$C$13>=1} -> TRUE
B28: {=$F$11:$F$13>=1} -> TRUE
B29: =$D$11>=第5题答案!$E$11 -> FALSE
B30: =$D$13<=第5题答案!$E$13 -> TRUE
B31: =$G$11>=第5题答案!$H$11 -> FALSE
B32: =$G$13<=第5题答案!$H$13 -> TRUE
B33: =$J$13<=第5题答案!$K$13 -> TRUE
B34: {=$I$11:$I$13>=1} -> TRUE
B35: ={100,100,0.000001,0.05,FALSE,FALSE,FALSE,1,1,1,0.0001,FALSE} -> 100

Sheet 第6题答案
A1: 贷款利率 | B1: 0.085
A3: 贷款投资数据 | B3: 净现金流
B4: 第0年 | C4: 第1年 | D4: 第2年 | E4: 第3年 | F4: 第4年 | G4: 第5年
A5: 现金流量 | B5: -40000 | C5: -15000 | D5: 5000 | E5: 20000 | F5: 30000 | G5: 18453.2
A6: 期初贷款余额 | C6: =B9 -> -40000 | D6: =C9 -> -58400 | E6: =D9 -> -58364 | F6: =E9 -> -43324.94 | G6: =F9 -> -17007.56
A7: 回报 | C7: =C5 -> -15000 | D7: =D5 -> 5000 | E7: =E5 -> 20000 | F7: =F5 -> 30000 | G7: =G5 -> 18453.2
A8: 贷款利息 | C8: =B9*$B$1 -> -3400 | D8: =C9*$B$1 -> -4964 | E8: =D9*$B$1 -> -4960.94 | F8: =E9*$B$1 -> -3682.6199 | G8: =F9*$B$1 -> -1445.6426
A9: 期末贷款余额 | B9: =B5 -> -40000 | C9: =SUM(C6:C8) -> -58400 | D9: =SUM(D6:D8) -> -58364 | E9: =SUM(E6:E8) -> -43324.94 | F9: =SUM(F6:F8) -> -17007.56 | G9: =SUM(G6:G8) -> -0.0024915

Sheet 第7题解答
P1: =I2 -> 项目B | Q1: =L2 -> 项目A
B2: 年数 | C2: 10 | I2: 项目B | L2: 项目A | P2: =C13 -> 766.71016 | Q2: =D13 -> 688.97673
B3: A方案设备残值 | C3: 150 | H3: 0 | I3: =-D8 -> -1000 | K3: 0 | L3: =-C8 -> -1500 | O3: 0.01 | P3: 1675.1849 | Q3: 1364.4364 | R3: =P3-Q3 -> 310.74852
B4: B方案设备残值 | C4: 90 | H4: 1 | I4: =$D$9 -> 20 | K4: 1 | L4: =$C$10 -> 400 | O4: 0.02 | P4: 1513.8315 | Q4: 1247.2932 | R4: =P4-Q4 -> 266.53831
B5: 年贴现率 | C5: 0.08 | H5: 2 | I5: =$D$9 -> 20 | K5: 2 | L5: =$C$10 -> 400 | O5: 0.03 | P5: 1364.6874 | Q5: 1137.9337 | R5: =P5-Q5 -> 226.7537
C6: 金额单位：万元 | H6: 3 | I6: =$D$9 -> 20 | K6: 3 | L6: =$C$10 -> 400 | O6: 0.04 | P6: 1226.632 | Q6: 1035.7724 | R6: =P6-Q6 -> 190.8596
C7: 项目A | D7: 项目B | H7: 4 | I7: =$D$9 -> 20 | K7: 4 | L7: =C12-C11 -> 200 | O7: 0.05 | P7: 1098.662 | Q7: 940.2715 | R7: =P7-Q7 -> 158.39052
B8: 第0年投资额 | C8: 1500 | D8: 1000 | H8: 5 | I8: =$D$9 -> 20 | K8: 5 | L8: =$C$12 -> 300 | O8: 0.06 | P8: 979.87716 | Q8: 850.93601 | R8: =P8-Q8 -> 128.94115
B9: 1至10年每月末收益 | D9: 20 | H9: 6 | I9: =$D$9 -> 20 | K9: 6 | L9: =$C$12 -> 300 | O9: 0.07 | P9: 869.46894 | Q9: 767.31075 | R9: =P9-Q9 -> 102.15819
B10: 第1年至第3年收益 | C10: 400 | H10: 7 | I10: =$D$9 -> 20 | K10: 7 | L10: =$C$12 -> 300 | O10: 0.08 | P10: 766.71016 | Q10: 688.97673 | R10: =P10-Q10 -> 77.733427
B11: 第4年维修设备投资金额 | C11: 100 | H11: 8 | I11: =$D$9 -> 20 | K11: 8 | L11: =$C$12 -> 300 | O11: 0.09 | P11: 670.94588 | Q11: 615.54821 | R11: =P11-Q11 -> 55.397666
B12: 第4年至第10年收益 | C12: 300 | H12: 9 | I12: =$D$9 -> 20 | K12: 9 | L12: =$C$12 -> 300 | O12: 0.1 | P12: 581.58548 | Q12: 546.66989 | R12: =P12-Q12 -> 34.915584
B13: 净现值 | C13: =NPV(C5,L4:L13)+L3 -> 766.71016 | D13: =-PV(C5/12,C2*12,D9,C4)-D8 -> 688.97673 | E13: =C13-D13 -> 77.733427 | H13: 10 | I13: =$D$9 -> 20 | K13: 10 | L13: =$C$12+C3 -> 450 | O13: 0.11 | P13: 498.09565 | Q13: 482.0144 | R13: =P13-Q13 -> 16.081244
B14: 年内部报酬率 | C14: =IRR(L3:L13) -> 0.18840883 | D14: =RATE(C2*12,D9,-D8,C4)*12 -> 0.21336079 | H14: 11 | I14: =$D$9 -> 20 | O14: 0.12 | P14: 419.99421 | Q14: 421.27997 | R14: =P14-Q14 -> -1.2857578
B15: 方案选择结论 | C15: =IF(MAX(C13:D13)>0,D15&"好","两个方案都不行") -> 项目A好 | D15: =INDEX(C7:D7,MATCH(MAX(C13:D13),C13:D13,0)) -> 项目A | H15: 12 | I15: =$D$9 -> 20 | O15: 0.13 | P15: 346.84468 | Q15: 364.18831 | R15: =P15-Q15 -> -17.343632
B16: 附表加插值法：两个项目相等时的年内部报酬率 | C16: =O20 -> 0.11925965 | H16: 13 | I16: =$D$9 -> 20 | O16: 0.14 | P16: 278.25144 | Q16: 310.48271 | R16: =P16-Q16 -> -32.231274
B17: 附表加插值法：两个项目相等时的净现值 | C17: =P20 -> 425.77642 | H17: 14 | I17: =$D$9 -> 20 | O17: 0.15 | P17: 213.85548 | Q17: 259.92624 | R17: =P17-Q17 -> -46.070761
H18: 15 | I18: =$D$9 -> 20
B19: 项目A的第2种解法： | H19: 16 | I19: =$D$9 -> 20 | O19: =INDEX(O3:O17,$S$19) -> 0.11 | P19: =INDEX(P3:P17,$S$19) -> 498.09565 | Q19: =INDEX(Q3:Q17,$S$19) -> 482.0144 | R19: =INDEX(R3:R17,$S$19) -> 16.081244 | S19: =MATCH(R20,R3:R17,-1) -> 11
B20: 使用PV()函数 | C20: =NPV(C5/12,I4:I123)+I3 -> 688.97673 | H20: 17 | I20: =$D$9 -> 20 | O20: =O19+($R$20-$R$19)/($R$21-$R$19)*(O21-O19) -> 0.11925965 | P20: =P19+($R$20-$R$19)/($R$21-$R$19)*(P21-P19) -> 425.77642 | Q20: =Q19+($R$20-$R$19)/($R$21-$R$19)*(Q21-Q19) -> 425.77642 | R20: 0
B21: 使用Rate()函数 | C21: =IRR(I3:I123,0.001)*12 -> 0.21336079 | H21: 18 | I21: =$D$9 -> 20 | O21: =INDEX(O3:O17,$S$21) -> 0.12 | P21: =INDEX(P3:P17,$S$21) -> 419.99421 | Q21: =INDEX(Q3:Q17,$S$21) -> 421.27997 | R21: =INDEX(R3:R17,$S$21) -> -1.2857578 | S21: =S19+1 -> 12
H22: 19 | I22: =$D$9 -> 20
H23: 20 | I23: =$D$9 -> 20
H24: 21 | I24: =$D$9 -> 20
H25: 22 | I25: =$D$9 -> 20
H26: 23 | I26: =$D$9 -> 20
H27: 24 | I27: =$D$9 -> 20
H28: 25 | I28: =$D$9 -> 20
H29: 26 | I29: =$D$9 -> 20
H30: 27 | I30: =$D$9 -> 20
H31: 28 | I31: =$D$9 -> 20
H32: 29 | I32: =$D$9 -> 20
H33: 30 | I33: =$D$9 -> 20
... H122: 119 | I122: =$D$9 -> 20
H123: 120 | I123: =$D$9+C4 -> 110

Sheet 第8题答案
H2: 零件寿命（小时）分布 | U2: 零件更换个数 | V2: 延误时间 | Y2: =D9 -> 90
C3: 每分钟停机成本 | D3: 5 | H3: 零件寿命 | I3: 概率 | J3: 累计概率 | O3: 零件寿命 | P3: 累计寿命 | Q3: 延误时间 | T3: SUM | U3: =SUM(U4:U23) -> 14 | V3: =SUM(V4:V23) -> 90 | X3: 1 | Y3: 96
C4: 更换1个零件的时间 | D4: 20 | H4: （小时） | J4: 0 | N4: 1 | O4: =INDEX($H$5:$H$14,MATCH(RAND(),$J$4:$J$14,1)) -> 1300 | P4: =O4 -> 1300 | Q4: =RANDBETWEEN($D$5,$D$6) -> 6 | T4: 1 | U4: =IF(P4>=20000,0,1) -> 1 | V4: =IF(U4=1,Q4,0) -> 6 | X4: 2 | Y4: 94
C5: 修理工的到达延误时间下限 | D5: 5 | H5: 1000 | I5: 0.05 | J5: =J4+I5 -> 0.05 | N5: 2 | O5: =INDEX($H$5:$H$14,MATCH(RAND(),$J$4:$J$14,1)) -> 1200 | P5: =P4+O5 -> 2500 | Q5: =RANDBETWEEN($D$5,$D$6) -> 7 | T5: 2 | U5: =IF(P5>=20000,0,1) -> 1 | V5: =IF(U5=1,Q5,0) -> 7 | X5: 3 | Y5: 91
C6: 修理工的到达延误时间上限 | D6: 8 | H6: 1100 | I6: 0.12 | J6: =J5+I6 -> 0.17 | N6: 3 | O6: =INDEX($H$5:$H$14,MATCH(RAND(),$J$4:$J$14,1)) -> 1600 | P6: =P5+O6 -> 4100 | Q6: =RANDBETWEEN($D$5,$D$6) -> 5 | T6: 3 | U6: =IF(P6>=20000,0,1) -> 1 | V6: =IF(U6=1,Q6,0) -> 5 | X6: 4 | Y6: 89
H7: 1200 | I7: 0.161 | J7: =J6+I7 -> 0.331 | N7: 4 | O7: =INDEX($H$5:$H$14,MATCH(RAND(),$J$4:$J$14,1)) -> 1600 | P7: =P6+O7 -> 5700 | Q7: =RANDBETWEEN($D$5,$D$6) -> 8 | T7: 4 | U7: =IF(P7>=20000,0,1) -> 1 | V7: =IF(U7=1,Q7,0) -> 8 | X7: 5 | Y7: 94
C8: 零件更换个数 | D8: =U3 -> 14 | H8: 1300 | I8: 0.193 | J8: =J7+I8 -> 0.524 | N8: 5 | O8: =INDEX($H$5:$H$14,MATCH(RAND(),$J$4:$J$14,1)) -> 1400 | P8: =P7+O8 -> 7100 | Q8: =RANDBETWEEN($D$5,$D$6) -> 8 | T8: 5 | U8: =IF(P8>=20000,0,1) -> 1 | V8: =IF(U8=1,Q8,0) -> 8 | X8: 6 | Y8: 95
C9: 修理工到达延误时间 | D9: =V3 -> 90 | H9: 1400 | I9: 0.183 | J9: =J8+I9 -> 0.707 | N9: 6 | O9: =INDEX($H$5:$H$14,MATCH(RAND(),$J$4:$J$14,1)) -> 1400 | P9: =P8+O9 -> 8500 | Q9: =RANDBETWEEN($D$5,$D$6) -> 6 | T9: 6 | U9: =IF(P9>=20000,0,1) -> 1 | V9: =IF(U9=1,Q9,0) -> 6 | X9: 7 | Y9: 89
C10: 修理工到达延误时的停机成本 | D10: =D9*D3 -> 450 | H10: 1500 | I10: 0.151 | J10: =J9+I10 -> 0.858 | N10: 7 | O10: =INDEX($H$5:$H$14,MATCH(RAND(),$J$4:$J$14,1)) -> 1300 | P10: =P9+O10 -> 9800 | Q10: =RANDBETWEEN($D$5,$D$6) -> 5 | T10: 7 | U10: =IF(P10>=20000,0,1) -> 1 | V10: =IF(U10=1,Q10,0) -> 5 | X10: 8 | Y10: 87
C11: 更换零件停机时间 | D11: =D8*D4 -> 280 | H11: 1600 | I11: 0.086 | J11: =J10+I11 -> 0.944 | N11: 8 | O11: =INDEX($H$5:$H$14,MATCH(RAND(),$J$4:$J$14,1)) -> 1300 | P11: =P10+O11 -> 11100 | Q11: =RANDBETWEEN($D$5,$D$6) -> 8 | T11: 8 | U11: =IF(P11>=20000,0,1) -> 1 | V11: =IF(U11=1,Q11,0) -> 8 | X11: 9 | Y11: 101
C12: 更换零件停机成本 | D12: =D11*D3 -> 1400 | H12: 1700 | I12: 0.028 | J12: =J11+I12 -> 0.972 | N12: 9 | O12: =INDEX($H$5:$H$14,MATCH(RAND(),$J$4:$J$14,1)) -> 1400 | P12: =P11+O12 -> 12500 | Q12: =RANDBETWEEN($D$5,$D$6) -> 7 | T12: 9 | U12: =IF(P12>=20000,0,1) -> 1 | V12: =IF(U12=1,Q12,0) -> 7 | X12: 10 | Y12: 84
H13: 1800 | I13: 0.016 | J13: =J12+I13 -> 0.988 | N13: 10 | O13: =INDEX($H$5:$H$14,MATCH(RAND(),$J$4:$J$14,1)) -> 1300 | P13: =P12+O13 -> 13800 | Q13: =RANDBETWEEN($D$5,$D$6) -> 5 | T13: 10 | U13: =IF(P13>=20000,0,1) -> 1 | V13: =IF(U13=1,Q13,0) -> 5 | X13: 11 | Y13: 99
C14: 30次模拟后的平均延误时间 | D14: =AVERAGE(Y3:Y32) -> 93.5 | H14: 1900 | I14: 0.012 | J14: =J13+I14 -> 1 | N14: 11 | O14: =INDEX($H$5:$H$14,MATCH(RAND(),$J$4:$J$14,1)) -> 1500 | P14: =P13+O14 -> 15300 | Q14: =RANDBETWEEN($D$5,$D$6) -> 6 | T14: 11 | U14: =IF(P14>=20000,0,1) -> 1 | V14: =IF(U14=1,Q14,0) -> 6 | X14: 12 | Y14: 85
N15: 12 | O15: =INDEX($H$5:$H$14,MATCH(RAND(),$J$4:$J$14,1)) -> 1500 | P15: =P14+O15 -> 16800 | Q15: =RANDBETWEEN($D$5,$D$6) -> 6 | T15: 12 | U15: =IF(P15>=20000,0,1) -> 1 | V15: =IF(U15=1,Q15,0) -> 6 | X15: 13 | Y15: 101
N16: 13 | O16: =INDEX($H$5:$H$14,MATCH(RAND(),$J$4:$J$14,1)) -> 1700 | P16: =P15+O16 -> 18500 | Q16: =RANDBETWEEN($D$5,$D$6) -> 7 | T16: 13 | U16: =IF(P16>=20000,0,1) -> 1 | V16: =IF(U16=1,Q16,0) -> 7 | X16: 14 | Y16: 87
N17: 14 | O17: =INDEX($H$5:$H$14,MATCH(RAND(),$J$4:$J$14,1)) -> 1100 | P17: =P16+O17 -> 19600 | Q17: =RANDBETWEEN($D$5,$D$6) -> 6 | T17: 14 | U17: =IF(P17>=20000,0,1) -> 1 | V17: =IF(U17=1,Q17,0) -> 6 | X17: 15 | Y17: 93
N18: 15 | O18: =INDEX($H$5:$H$14,MATCH(RAND(),$J$4:$J$14,1)) -> 1100 | P18: =P17+O18 -> 20700 | Q18: =RANDBETWEEN($D$5,$D$6) -> 5 | T18: 15 | U18: =IF(P18>=20000,0,1) -> 0 | V18: =IF(U18=1,Q18,0) -> 0 | X18: 16 | Y18: 88
N19: 16 | O19: =INDEX($H$5:$H$14,MATCH(RAND(),$J$4:$J$14,1)) -> 1400 | P19: =P18+O19 -> 22100 | Q19: =RANDBETWEEN($D$5,$D$6) -> 8 | T19: 16 | U19: =IF(P19>=20000,0,1) -> 0 | V19: =IF(U19=1,Q19,0) -> 0 | X19: 17 | Y19: 98
N20: 17 | O20: =INDEX($H$5:$H$14,MATCH(RAND(),$J$4:$J$14,1)) -> 1500 | P20: =P19+O20 -> 23600 | Q20: =RANDBETWEEN($D$5,$D$6) -> 6 | T20: 17 | U20: =IF(P20>=20000,0,1) -> 0 | V20: =IF(U20=1,Q20,0) -> 0 | X20: 18 | Y20: 82
N21: 18 | O21: =INDEX($H$5:$H$14,MATCH(RAND(),$J$4:$J$14,1)) -> 1400 | P21: =P20+O21 -> 25000 | Q21: =RANDBETWEEN($D$5,$D$6) -> 6 | T21: 18 | U21: =IF(P21>=20000,0,1) -> 0 | V21: =IF(U21=1,Q21,0) -> 0 | X21: 19 | Y21: 101
N22: 19 | O22: =INDEX($H$5:$H$14,MATCH(RAND(),$J$4:$J$14,1)) -> 1700 | P22: =P21+O22 -> 26700 | Q22: =RANDBETWEEN($D$5,$D$6) -> 5 | T22: 19 | U22: =IF(P22>=20000,0,1) -> 0 | V22: =IF(U22=1,Q22,0) -> 0 | X22: 20 | Y22: 84
N23: 20 | O23: =INDEX($H$5:$H$14,MATCH(RAND(),$J$4:$J$14,1)) -> 1500 | P23: =P22+O23 -> 28200 | Q23: =RANDBETWEEN($D$5,$D$6) -> 5 | T23: 20 | U23: =IF(P23>=20000,0,1) -> 0 | V23: =IF(U23=1,Q23,0) -> 0 | X23: 21 | Y23: 97
X24: 22 | Y24: 104
X25: 23 | Y25: 94
X26: 24 | Y26: 95
X27: 25 | Y27: 96
X28: 26 | Y28: 96
X29: 27 | Y29: 95
X30: 28 | Y30: 88
X31: 29 | Y31: 101
X32: 30 | Y32: 101
